{
    "simulation_parameters": {
        "number_of_regional_warehouses": 2,
        "rw_inventory_limit": 100,
        "cw_inventory_limit": 200,
        "demand": [3, 5],
        "sim_length": 80,
        "lead_time": 3,
        "shipment_amount": [15],
        "manufacturer": true,
        "cw_shipment_amount": 30,
        "mf_prod_capacity": 20,
        "customer_priorities": [1, 1, 1],
        "shipment_var_cost_per_unit": 0.01,
        "shipment_fixed_cost": 0.15,
        "inventory_holding_cost_multiplier": 1,
        "cw_inventory_holding_cost_multiplier": 0.5,
        "demand_fluctuation": 1,
        "lead_time_fluctuation": 0,
        "use_single_value_action_space": true,
        "rw_inventory_cost_drop_off": 0.5,
        "cw_inventory_cost_drop_off": 0.2,
        "use_advanced_demand_simulation": true,
        "demand_curve_length_multiplier": 1,
        "manufacturer_inventory_limit": 200
    },
    "rl_model_training": {
        "rl_model": "DQN",
        "num_of_training_steps": 10000,
        "training_episodes": 125,
        "training_rewards": [0, -3.15, -2.59, -4.49, -4.62, -3.9, -6.38, -3.07, -4.11, -5.87, -4.94, -4.71, -4.21, -3.63, -3.2, -3.21, -3.78, -5.33, -2.39, -5.7, -4.73, -4.62, -2.76, -5.17, -4.57, -2.83, -5.39, -5.55, -4.84, -5.07, -2.43, -4.72, -4.45, -4.4, -1.94, -5.18, -3.6, -5.61, -4.87, -5.58, -5.51, -5.77, -2.15, -3.67, -4.2, -4.33, -4.2, -3.07, -3.42, -4.9, -3.04, -4.36, -3.62, -2.99, -4.57, -4.27, -3.63, -3.11, -5.33, -4.76, -6.55, -3.92, -3.48, -2.77, -3.25, -4.96, -4.79, -4.12, -5.48, -3.52, -4.57, -4.55, -5.15, -4.54, -4.77, -5.56, -5.28, -1.86, -5.17, -4.17, -5.29, -3.62, -6.5, -3.71, -4.97, -3.9, -4.38, -4.43, -4.92, -4.85, -5.1, -4.71, -2.29, -4.42, -5.78, -3.89, -4.58, -4.25, -4.55, -3.17, -3.72, -4.69, -4.9, -4.07, -2.42, -3.08, -5.32, -3.44, -3.33, -4.18, -4.79, -2.89, -3.93, -5.13, -3.35, -3.52, -5.08, -3.56, -5.47, -4.95, -4.03, -5.49, -5.14, -3.1, -5.45, -4.79]
    },
    "simulation_run_data": {
        "stats": {
            "total_shipments": 177,
            "total_lost_sales": 0,
            "total_reward_gained": -7.04
        },
        "regional_warehouse_1": {
            "inventory": [31, 29, 27, 25, 38, 36, 49, 62, 60, 58, 56, 69, 66, 63, 75, 72, 69, 66, 62, 73, 84, 95, 91, 96, 96, 92, 88, 84, 95, 96, 92, 88, 84, 80, 76, 72, 68, 64, 61, 58, 55, 52, 49, 46, 43, 40, 37, 34, 31, 43, 40, 52, 49, 61, 73, 70, 82, 94, 97, 94, 97, 98, 98, 96, 98, 98, 98, 96, 98, 98, 98, 96, 98, 98, 98, 96, 98, 98, 98, 96],
            "actions": [0, 1, 0, 1, 1, 1, 0, 1, 1, 0, 0, 1, 1, 1, 1, 1, 1, 1, 1, 1, 1, 1, 1, 0, 0, 1, 1, 1, 0, 1, 1, 1, 1, 1, 1, 0, 1, 1, 1, 1, 1, 1, 1, 1, 0, 1, 1, 0, 1, 1, 1, 1, 0, 1, 1, 1, 0, 1, 1, 1, 0, 1, 1, 1, 0, 1, 1, 1, 0, 1, 1, 1, 0, 1, 1, 1, 0, 1, 1, 1],
            "demand": [2, 2, 2, 2, 2, 2, 2, 2, 2, 2, 2, 2, 3, 3, 3, 3, 3, 3, 4, 4, 4, 4, 4, 4, 4, 4, 4, 4, 4, 4, 4, 4, 4, 4, 4, 4, 4, 4, 3, 3, 3, 3, 3, 3, 3, 3, 3, 3, 3, 3, 3, 3, 3, 3, 3, 3, 3, 3, 3, 3, 3, 2, 2, 2, 2, 2, 2, 2, 2, 2, 2, 2, 2, 2, 2, 2, 2, 2, 2, 2]
        },
        "regional_warehouse_2": {
            "inventory": [28, 23, 18, 14, 25, 36, 47, 43, 39, 35, 31, 42, 38, 49, 45, 41, 37, 32, 27, 38, 49, 60, 56, 67, 78, 74, 85, 96, 96, 96, 92, 88, 84, 80, 76, 72, 68, 63, 58, 53, 48, 43, 38, 33, 28, 23, 18, 13, 8, 18, 13, 23, 18, 28, 38, 48, 58, 68, 62, 71, 80, 89, 83, 92, 94, 94, 88, 94, 94, 94, 88, 94, 94, 94, 88, 94, 95, 95, 90, 95],
            "actions": [0, 1, 1, 1, 1, 1, 1, 1, 1, 1, 1, 1, 1, 1, 1, 1, 1, 1, 1, 1, 1, 1, 1, 1, 1, 1, 1, 1, 1, 1, 1, 1, 1, 1, 1, 0, 1, 1, 1, 1, 1, 1, 1, 1, 0, 1, 1, 0, 1, 1, 1, 1, 1, 1, 1, 1, 1, 1, 1, 1, 1, 1, 1, 1, 1, 1, 1, 1, 1, 1, 1, 1, 1, 1, 1, 1, 1, 1, 1, 1],
            "demand": [5, 5, 5, 4, 4, 4, 4, 4, 4, 4, 4, 4, 4, 4, 4, 4, 4, 5, 5, 4, 4, 4, 4, 4, 4, 4, 4, 4, 4, 4, 4, 4, 4, 4, 4, 4, 4, 5, 5, 5, 5, 5, 5, 5, 5, 5, 5, 5, 5, 5, 5, 5, 5, 5, 5, 5, 5, 5, 6, 6, 6, 6, 6, 6, 6, 6, 6, 6, 6, 6, 6, 6, 6, 6, 6, 6, 5, 5, 5, 5]
        },
        "central_warehouse": {
            "inventory": [66, 36, 21, 21, 6, 6, 6, 6, 6, 6, 21, 6, 6, 6, 6, 6, 6, 6, 6, 6, 6, 6, 6, 21, 36, 36, 6, 6, 6, 6, 6, 6, 6, 6, 6, 6, 6, 6, 6, 6, 6, 6, 6, 6, 6, 6, 6, 6, 6, 6, 6, 6, 21, 21, 21, 6, 21, 21, 21, 6, 21, 21, 21, 6, 21, 21, 21, 6, 21, 21, 21, 6, 21, 21, 21, 6, 21, 21, 21, 6],
            "actions": [1, 0, 0, 0, 0, 1, 0, 1, 0, 0, 0, 0, 0, 1, 1, 1, 0, 1, 1, 0, 1, 1, 1, 0, 0, 0, 0, 0, 0, 0, 0, 0, 0, 0, 0, 0, 0, 0, 0, 0, 0, 0, 0, 1, 0, 1, 0, 1, 1, 1, 1, 1, 0, 1, 1, 1, 0, 1, 1, 1, 0, 1, 1, 1, 0, 1, 1, 1, 0, 1, 1, 1, 0, 1, 1, 1, 0, 1, 1, 1]
        },
        "manufacturer": {
            "inventory": [56, 76, 96, 116, 136, 126, 146, 136, 156, 176, 196, 200, 200, 170, 160, 150, 170, 160, 150, 170, 160, 150, 140, 160, 180, 200, 200, 200, 200, 200, 200, 200, 200, 200, 200, 200, 200, 200, 200, 200, 200, 200, 200, 170, 190, 170, 190, 170, 160, 150, 140, 130, 150, 140, 130, 120, 140, 130, 120, 110, 130, 120, 110, 100, 120, 110, 100, 90, 110, 100, 90, 80, 100, 90, 80, 70, 90, 80, 70, 60]
        }
    }
}